utils_package/__init__.py
utils_package/logger.py
utils_package/util_funcs.py
utils_package_Martin36-0.0.8.dist-info/LICENSE
utils_package_Martin36-0.0.8.dist-info/METADATA
utils_package_Martin36-0.0.8.dist-info/WHEEL
utils_package_Martin36-0.0.8.dist-info/top_level.txt
utils_package_Martin36-0.0.8.dist-info/RECORD
